libwebview/__init__.py
libwebview/wrapper.py
libwebview/lib/x86_64/libwebview_edge.dll
libwebview-1.1.1.dist-info/LICENSE
libwebview-1.1.1.dist-info/METADATA
libwebview-1.1.1.dist-info/WHEEL
libwebview-1.1.1.dist-info/top_level.txt
libwebview-1.1.1.dist-info/RECORD
