Metadata-Version: 2.1
Name: libwebview
Version: 1.1.1
Summary: Library for application development using WebView
Author: Dmitriy Lukovenko
Author-email: mludima23@gmail.com
License: MIT License
Project-URL: Documentation, https://github.com/a3st/libwebview/wiki
Project-URL: Source, https://github.com/a3st/libwebview
Classifier: Programming Language :: Python :: 3
Classifier: License :: OSI Approved :: MIT License
Classifier: Operating System :: Android
Classifier: Operating System :: Microsoft :: Windows
Classifier: Operating System :: POSIX :: Linux
Requires-Python: >=3.11
License-File: LICENSE
